darr/__init__.py
darr/array.py
darr/basedatadir.py
darr/datadir.py
darr/metadata.py
darr/numtype.py
darr/raggedarray.py
darr/readcodearray.py
darr/readcoderaggedarray.py
darr/utils.py
darr-0.6.3.dist-info/METADATA
darr-0.6.3.dist-info/WHEEL
darr-0.6.3.dist-info/licenses/LICENSE
darr-0.6.3.dist-info/RECORD
