Metadata-Version: 2.4
Name: darr
Version: 0.6.3
Summary: Stores NumPy arrays in a way that is self-documented and tool-independent.
Project-URL: Homepage, https://github.com/gbeckers/Darr
Project-URL: Repository, https://github.com/gbeckers/Darr.git
Project-URL: Documentation, https://darr.readthedocs.io/en/latest/
Author-email: Gabriel Beckers <g.j.l.beckers@uu.nl>
License-Expression: BSD-3-Clause
License-File: LICENSE
Keywords: array,data-science,data-sharing,data-storage,idl,interoperability,jagged-array,julia,maple,mathematica,matlab,numeric,octave,r,ragged-array,science,scilab
Classifier: Development Status :: 4 - Beta
Classifier: Intended Audience :: Developers
Classifier: Intended Audience :: Education
Classifier: Intended Audience :: Information Technology
Classifier: Intended Audience :: Science/Research
Classifier: Operating System :: OS Independent
Classifier: Programming Language :: Python :: 3
Requires-Python: >=3.9
Requires-Dist: numpy
